orthomap/__init__.py
orthomap/__main__.py
orthomap/cds2aa.py
orthomap/datasets.py
orthomap/eggnog2orthomap.py
orthomap/gtf2t2g.py
orthomap/ncbitax.py
orthomap/of2orthomap.py
orthomap/orthomap2tei.py
orthomap/plaza2orthomap.py
orthomap/qlin.py
orthomap-0.0.1.dist-info/LICENSE
orthomap-0.0.1.dist-info/METADATA
orthomap-0.0.1.dist-info/WHEEL
orthomap-0.0.1.dist-info/entry_points.txt
orthomap-0.0.1.dist-info/top_level.txt
orthomap-0.0.1.dist-info/RECORD
