Metadata-Version: 2.1
Name: orthomap
Version: 0.0.1
Summary: extract orthomap from OrthoFinder output for query species
Author-email: Kristian K Ullrich <ullrich@evolbio.mpg.de>, Nikoleta E Glynatsi <glynatsi@evolbio.mpg.de>
Maintainer-email: Kristian K Ullrich <ullrich@evolbio.mpg.de>
License: GPLv3
Project-URL: Homepage, https://github.com/kullrich/orthomap
Project-URL: Bug Tracker, https://github.com/kullrich/orthomap/issues
Project-URL: documentation, https://orthomap.readthedocs.io/en/latest/
Project-URL: repository, https://github.com/kullrich/orthomap
Keywords: orthomap,gene age,orthologs,phylostratigraphy,single-cell
Classifier: Development Status :: 3 - Alpha
Classifier: License :: OSI Approved :: GNU General Public License v3 (GPLv3)
Classifier: Topic :: Scientific/Engineering :: Bio-Informatics
Classifier: Programming Language :: Python :: 3.8
Classifier: Programming Language :: Python :: 3.9
Classifier: Programming Language :: Python :: 3.10
Classifier: Intended Audience :: Science/Research
Classifier: Intended Audience :: Education
Requires-Python: >=3.8
License-File: LICENSE
Requires-Dist: setuptools (>=67.5.1)
Requires-Dist: numpy (<1.24)
Requires-Dist: numba
Requires-Dist: scipy
Requires-Dist: pandas (>=1.5.3)
Requires-Dist: ete3
Requires-Dist: anndata
Requires-Dist: scanpy (>=1.9.3)
Requires-Dist: seaborn
Requires-Dist: statannot
Requires-Dist: harmonypy (>=0.0.9)
Requires-Dist: louvain (>=0.8.0)
Requires-Dist: umap-learn (>=0.5.3)
Requires-Dist: alive-progress
Requires-Dist: biopython
Requires-Dist: wget (>=3.2)
Requires-Dist: pytest
Requires-Dist: pip
